metaego/__init__.py
metaego/nn/__init__.py
metaego/nn/linear.py
metaego/nn/vit.py
metaego-0.1.1.dist-info/METADATA
metaego-0.1.1.dist-info/WHEEL
metaego-0.1.1.dist-info/RECORD
