Metadata-Version: 2.1
Name: metaego
Version: 0.1.1
Summary: Official repo for Meta-models.
Author: Zhuolin Fu
Author-email: fzhuolin@gmail.com
Requires-Python: >=3.10,<4.0
Classifier: Programming Language :: Python :: 3
Classifier: Programming Language :: Python :: 3.10
Classifier: Programming Language :: Python :: 3.11
Classifier: Programming Language :: Python :: 3.12
Requires-Dist: einops (>=0.8.1,<0.9.0)
Requires-Dist: torch (>=2.0.0,<3.0.0)
